GOES/__init__.py
GOES/downloads/__init__.py
GOES/downloads/download_data.py
GOES/processing/__init__.py
GOES/processing/processing_data.py
goes-3.4.4.dist-info/licenses/LICENSE
goes-3.4.4.dist-info/METADATA
goes-3.4.4.dist-info/WHEEL
goes-3.4.4.dist-info/top_level.txt
goes-3.4.4.dist-info/RECORD
