Metadata-Version: 2.4
Name: GOES
Version: 3.4.4
Summary: Python package to download and manipulate GOES-16/17/18/19 data.
Home-page: https://github.com/joaohenry23/GOES
Author: Joao Henry Huamán Chinchay
Author-email: joaohenry23@gmail.com
License: BSD-3-Clause
Classifier: Programming Language :: Python :: 2
Classifier: Programming Language :: Python :: 3
Classifier: Operating System :: OS Independent
Requires-Python: >=2.7
License-File: LICENSE
Requires-Dist: numpy
Requires-Dist: cftime>1.1
Requires-Dist: requests
Requires-Dist: s3fs
Requires-Dist: pyproj
Requires-Dist: netCDF4
Dynamic: author
Dynamic: author-email
Dynamic: classifier
Dynamic: description
Dynamic: description-content-type
Dynamic: home-page
Dynamic: license
Dynamic: license-file
Dynamic: requires-dist
Dynamic: requires-python
Dynamic: summary
